respeecher/__init__.py
respeecher/client.py
respeecher/core/__init__.py
respeecher/core/api_error.py
respeecher/core/client_wrapper.py
respeecher/core/datetime_utils.py
respeecher/core/events.py
respeecher/core/file.py
respeecher/core/force_multipart.py
respeecher/core/http_client.py
respeecher/core/http_response.py
respeecher/core/jsonable_encoder.py
respeecher/core/pydantic_utilities.py
respeecher/core/query_encoder.py
respeecher/core/remove_none_from_dict.py
respeecher/core/request_options.py
respeecher/core/serialization.py
respeecher/environment.py
respeecher/py.typed
respeecher/tts/__init__.py
respeecher/tts/client.py
respeecher/tts/raw_client.py
respeecher/tts/requests/__init__.py
respeecher/tts/requests/bytes_generation_request.py
respeecher/tts/requests/cancellation_request.py
respeecher/tts/requests/chunk.py
respeecher/tts/requests/contextful_chunk.py
respeecher/tts/requests/contextful_generation_request.py
respeecher/tts/requests/done.py
respeecher/tts/requests/generation_request.py
respeecher/tts/requests/output_format.py
respeecher/tts/requests/response.py
respeecher/tts/requests/server_sent_event.py
respeecher/tts/requests/streaming_error.py
respeecher/tts/requests/streaming_generation_request.py
respeecher/tts/requests/streaming_output_format.py
respeecher/tts/requests/voice.py
respeecher/tts/socket_client.py
respeecher/tts/types/__init__.py
respeecher/tts/types/bytes_generation_request.py
respeecher/tts/types/cancellation_request.py
respeecher/tts/types/chunk.py
respeecher/tts/types/contextful_chunk.py
respeecher/tts/types/contextful_generation_request.py
respeecher/tts/types/done.py
respeecher/tts/types/generation_request.py
respeecher/tts/types/output_format.py
respeecher/tts/types/response.py
respeecher/tts/types/server_sent_event.py
respeecher/tts/types/streaming_encoding.py
respeecher/tts/types/streaming_error.py
respeecher/tts/types/streaming_generation_request.py
respeecher/tts/types/streaming_output_format.py
respeecher/tts/types/voice.py
respeecher-1.0.0.dist-info/METADATA
respeecher-1.0.0.dist-info/WHEEL
respeecher-1.0.0.dist-info/RECORD
